ALU/ALU32.v
module ALU(
        //根据数据通路定义输入和输出
        input [31:0] ReadData1,
        input [31:0] ReadData2,
        input [31:0] Ext,
        input [31:0] Sa,
        input [2:0] ALUop,
        input ALUSrcA, ALUSrcB,

        output  zero, 
        output reg [31:0] Result
    );

    //两个输入端口
    wire [31:0] InA;
    wire [31:0] InB;

    assign InA = ALUSrcA ? Sa : ReadData1;
    assign InB = ALUSrcB ? Ext : ReadData2;

    assign zero = (Result == 0) ? 1 : 0;

    //只要输入的值发生变化，就执行计算
    always @(*) begin
        case(ALUop) //根据ALUop实现相应的运算功能
            3'b000 : 
                Result = InA + InB;
            3'b001:
                Result = InA - InB;
            3'b010:
                Result = InB << InA;
            3'b011:
                Result = InA | InB;
            3'b100:
                Result = InA & InB;
            3'b101:
                Result = (InA < InB) ? 1 : 0;
            3'b110: 
                Result = (((InA < InB) && (InA[31] == InB[31])) || 
                    ((InA[31] == 1) && (InB[31] == 0))) ? 1 : 0;
            3'b111:
                Result = InA ^~ InB;
            default:
                Result = 32'h0000;
        endcase
    end

endmodule

ALU/ALU32_Test.v
`include "ALU32.v"

module ALU_sim();

    //input
    reg [31:0] ReadData1;
    reg [31:0] ReadData2;
    reg [31:0] Ext;
    reg [31:0] Sa;
    reg [2:0] ALUop;
    reg ALUSrcA, ALUSrcB;

    //output
    wire zero;
    wire [31:0] Result;

    ALU uut(
        .ReadData1(ReadData1),
        .ReadData2(ReadData2),
        .Ext(Ext),
        .Sa(Sa),
        .ALUop(ALUop),
        .ALUSrcA(ALUSrcA),
        .ALUSrcB(ALUSrcB),
        .zero(zero),
        .Result(Result)
    );

    initial begin
        //record
        $dumpfile("ALU32.vcd");
        $dumpvars(0, ALU_sim);

        //add1
        ReadData1 = 0;
        ReadData2 = 0;
        Ext = 1;
        Sa = 1;
        ALUop = 3'b000;
        ALUSrcA = 0;
        ALUSrcB = 0;

        //add2
        #50;
        ReadData1 = 0;
        ReadData2 = 0;
        Ext = 1;
        Sa = 1;
        ALUop = 3'b000;
        ALUSrcA = 1;
        ALUSrcB = 0;

        //add3
        #50;
        ReadData1 = 0;
        ReadData2 = 0;
        Ext = 1;
        Sa = 1;
        ALUop = 3'b000;
        ALUSrcA = 0;
        ALUSrcB = 1;

        //add4
        #50;
        ReadData1 = 0;
        ReadData2 = 0;
        Ext = 1;
        Sa = 1;
        ALUop = 3'b000;
        ALUSrcA = 1;
        ALUSrcB = 1;

        //sub1
        #50;
        ReadData1 = 1;
        ReadData2 = 2;
        Ext = 3;
        Sa = 4;
        ALUop = 3'b001;
        ALUSrcA = 0;
        ALUSrcB = 0;

        //sub2
        #50;
        ReadData1 = 1;
        ReadData2 = 2;
        Ext = 3;
        Sa = 4;
        ALUop = 3'b001;
        ALUSrcA = 1;
        ALUSrcB = 0;

        //sub3
        #50;
        ReadData1 = 1;
        ReadData2 = 2;
        Ext = 3;
        Sa = 4;
        ALUop = 3'b001;
        ALUSrcA = 0;
        ALUSrcB = 1;

        //sub4
        #50;
        ReadData1 = 1;
        ReadData2 = 2;
        Ext = 3;
        Sa = 4;
        ALUop = 3'b001;
        ALUSrcA = 1;
        ALUSrcB = 1;

        //left_shift1
        #50;
        ReadData1 = 1;
        ReadData2 = 2;
        Ext = 2;
        Sa = 4;
        ALUop = 3'b010;
        ALUSrcA = 0;
        ALUSrcB = 0;

        //left_shift2
        #50;
        ReadData1 = 1;
        ReadData2 = 2;
        Ext = 2;
        Sa = 4;
        ALUop = 3'b010;
        ALUSrcA = 1;
        ALUSrcB = 0;

        //left_shift3
        #50;
        ReadData1 = 1;
        ReadData2 = 2;
        Ext = 2;
        Sa = 4;
        ALUop = 3'b010;
        ALUSrcA = 0;
        ALUSrcB = 1;

        //left_shift4
        #50;
        ReadData1 = 1;
        ReadData2 = 2;
        Ext = 2;
        Sa = 4;
        ALUop = 3'b010;
        ALUSrcA = 1;
        ALUSrcB = 1;

        //or1
        #50;
        ReadData1 = 1;
        ReadData2 = 2;
        Ext = 2;
        Sa = 4;
        ALUop = 3'b011;
        ALUSrcA = 0;
        ALUSrcB = 0;

        //or2
        #50;
        ReadData1 = 1;
        ReadData2 = 2;
        Ext = 2;
        Sa = 4;
        ALUop = 3'b011;
        ALUSrcA = 1;
        ALUSrcB = 0;

        //or3
        #50;
        ReadData1 = 1;
        ReadData2 = 2;
        Ext = 2;
        Sa = 4;
        ALUop = 3'b011;
        ALUSrcA = 0;
        ALUSrcB = 1;

        //or4
        #50;
        ReadData1 = 1;
        ReadData2 = 2;
        Ext = 2;
        Sa = 4;
        ALUop = 3'b011;
        ALUSrcA = 1;
        ALUSrcB = 1;

        //and1
        #50;
        ReadData1 = 1;
        ReadData2 = 2;
        Ext = 2;
        Sa = 4;
        ALUop = 3'b100;
        ALUSrcA = 0;
        ALUSrcB = 0;

        //and2
        #50;
        ReadData1 = 1;
        ReadData2 = 2;
        Ext = 2;
        Sa = 4;
        ALUop = 3'b100;
        ALUSrcA = 1;
        ALUSrcB = 0;

        //and3
        #50;
        ReadData1 = 1;
        ReadData2 = 2;
        Ext = 2;
        Sa = 4;
        ALUop = 3'b100;
        ALUSrcA = 0;
        ALUSrcB = 1;

        //and4
        #50;
        ReadData1 = 1;
        ReadData2 = 2;
        Ext = 2;
        Sa = 4;
        ALUop = 3'b100;
        ALUSrcA = 1;
        ALUSrcB = 1;

        //不带符号比较1
        #50;
        ReadData1 = 1;
        ReadData2 = 2;
        Ext = 2;
        Sa = 1;
        ALUop = 3'b101;
        ALUSrcA = 0;
        ALUSrcB = 0;

        //不带符号比较2
        #50;
        ReadData1 = 1;
        ReadData2 = 2;
        Ext = 2;
        Sa = 1;
        ALUop = 3'b101;
        ALUSrcA = 1;
        ALUSrcB = 0;

        //不带符号比较3
        #50;
        ReadData1 = 1;
        ReadData2 = 2;
        Ext = 2;
        Sa = 1;
        ALUop = 3'b101;
        ALUSrcA = 0;
        ALUSrcB = 1;

        //不带符号比较4
        #50;
        ReadData1 = 1;
        ReadData2 = 2;
        Ext = 2;
        Sa = 1;
        ALUop = 3'b101;
        ALUSrcA = 1;
        ALUSrcB = 1;

        //带符号比较1
        #50;
        ReadData1 = 1;
        ReadData2 = 2;
        Ext = 2;
        Sa = 1;
        ALUop = 3'b110;
        ALUSrcA = 0;
        ALUSrcB = 0;

        //带符号比较2
        #50;
        ReadData1 = 1;
        ReadData2 = 2;
        Ext = 2;
        Sa = 1;
        ALUop = 3'b110;
        ALUSrcA = 1;
        ALUSrcB = 0;

        //带符号比较3
        #50;
        ReadData1 = 1;
        ReadData2 = 2;
        Ext = 2;
        Sa = 1;
        ALUop = 3'b110;
        ALUSrcA = 0;
        ALUSrcB = 1;

        //带符号比较4
        #50;
        ReadData1 = 1;
        ReadData2 = 2;
        Ext = 2;
        Sa = 1;
        ALUop = 3'b110;
        ALUSrcA = 1;
        ALUSrcB = 1;

        //nor1
        #50;
        ReadData1 = 1;
        ReadData2 = 2;
        Ext = 2;
        Sa = 1;
        ALUop = 3'b111;
        ALUSrcA = 0;
        ALUSrcB = 0;

        //nor2
        #50;
        ReadData1 = 1;
        ReadData2 = 2;
        Ext = 2;
        Sa = 1;
        ALUop = 3'b111;
        ALUSrcA = 1;
        ALUSrcB = 0;

        //nor3
        #50;
        ReadData1 = 1;
        ReadData2 = 2;
        Ext = 2;
        Sa = 1;
        ALUop = 3'b111;
        ALUSrcA = 0;
        ALUSrcB = 1;

        //nor4
        #50;
        ReadData1 = 1;
        ReadData2 = 2;
        Ext = 2;
        Sa = 1;
        ALUop = 3'b111;
        ALUSrcA = 1;
        ALUSrcB = 1;

        //stop
        #50;
        $stop;
    end

endmodule

ALU/ALU32.vcd
$date
	Thu Nov 14 11:02:32 2019
$end
$version
	Icarus Verilog
$end
$timescale
	1s
$end
$scope module ALU_sim $end
$var wire 1 ! zero $end
$var wire 32 " Result [31:0] $end
$var reg 1 # ALUSrcA $end
$var reg 1 $ ALUSrcB $end
$var reg 3 % ALUop [2:0] $end
$var reg 32 & Ext [31:0] $end
$var reg 32 ' ReadData1 [31:0] $end
$var reg 32 ( ReadData2 [31:0] $end
$var reg 32 ) Sa [31:0] $end
$scope module uut $end
$var wire 1 # ALUSrcA $end
$var wire 1 $ ALUSrcB $end
$var wire 3 * ALUop [2:0] $end
$var wire 32 + Ext [31:0] $end
$var wire 32 , ReadData1 [31:0] $end
$var wire 32 - ReadData2 [31:0] $end
$var wire 32 . Sa [31:0] $end
$var wire 1 ! zero $end
$var wire 32 / InB [31:0] $end
$var wire 32 0 InA [31:0] $end
$var reg 32 1 Result [31:0] $end
$upscope $end
$upscope $end
$enddefinitions $end
#0
$dumpvars
b0 1
b0 0
b0 /
b1 .
b0 -
b0 ,
b1 +
b0 *
b1 )
b0 (
b0 '
b1 &
b0 %
0$
0#
b0 "
1!
$end
#50
0!
b1 "
b1 1
b1 0
1#
#100
b1 /
b0 0
1$
0#
#150
b10 "
b10 1
b1 0
1#
#200
b11111111111111111111111111111111 "
b11111111111111111111111111111111 1
b10 /
0$
0#
b1 %
b1 *
b100 )
b100 .
b11 &
b11 +
b10 (
b10 -
b1 '
b1 ,
#250
b10 "
b10 1
b100 0
1#
#300
b11111111111111111111111111111110 "
b11111111111111111111111111111110 1
b11 /
b1 0
1$
0#
#350
b1 "
b1 1
b100 0
1#
#400
b1 0
b100 "
b100 1
b10 /
0$
0#
b10 %
b10 *
b10 &
b10 +
#450
b100000 "
b100000 1
b100 0
1#
#500
b100 "
b100 1
b1 0
1$
0#
#550
b100000 "
b100000 1
b100 0
1#
#600
b1 0
b11 "
b11 1
0$
0#
b11 %
b11 *
#650
b110 "
b110 1
b100 0
1#
#700
b11 "
b11 1
b1 0
1$
0#
#750
b110 "
b110 1
b100 0
1#
#800
1!
b1 0
b0 "
b0 1
0$
0#
b100 %
b100 *
#850
b100 0
1#
#900
b1 0
1$
0#
#950
b100 0
1#
#1000
b1 0
0$
0#
b101 %
b101 *
b1 )
b1 .
#1050
1#
#1100
1$
0#
#1150
1#
#1200
0!
b1 "
b1 1
0$
0#
b110 %
b110 *
#1250
1#
#1300
1$
0#
#1350
1#
#1400
b11111111111111111111111111111100 "
b11111111111111111111111111111100 1
0$
0#
b111 %
b111 *
#1450
1#
#1500
1$
0#
#1550
1#
