ALU/ALU32.v
module ALU32(
    input [2 : 0] ALUopcode,
    input [31 : 0] rega,
    input [31 : 0] regb,
    output reg [31 : 0] result,
    output zero, sign  
);

assign zero = (result == 0) ? 1 : 0;
assign sign = (result[31] == 0) ? 0 : 1;

always @(ALUopcode or rega or regb) begin
    case (ALUopcode)
        3'b000 : result = rega + regb;
        3'b001 : result = rega - regb;
        3'b010 : result = rega & regb;
        3'b011 : result = rega | regb;
        3'b100 : result = (rega < regb) ? 1 : 0;//不带符号比较
        3'b101 : begin
                    if(rega < regb && 
                        ((rega[31] == 0 && regb[31] == 0) || 
                            (rega[31] == 1 && regb[31] == 1))) result = 1;
                    
                    else if(rega[31] == 0 && regb[31] == 1) result = 0;
                    else if(rega[31] == 1 && regb[31] == 0) result = 1;
                    else result = 0;
                  end
        default : begin
                    result = 8'h00000000;
                    $display("no match");
                  end
    endcase
end

endmodule

ALU/ALU32_Test.v
`include "ALU32.v"

module ALU32_sim();

//inputs
reg [2:0] ALUopcode;
reg [31:0] rega;
reg [31:0] regb;

//outputs
wire [31:0] result;
wire zero;
wire sign;

//Instantiate the Unit Under Test(UUT)
ALU32 uut(
    .ALUopcode(ALUopcode),
    .rega(rega),
    .regb(regb),
    .result(result),
    .sign(sign),
    .zero(zero)
);

initial 
    begin
        //record
        $dumpfile("ALU32.vcd");
        $dumpvars(0, ALU32_sim);

        //initial Inputs
            ALUopcode = 0;
            rega = 0;
            regb = 0;
        
        //wait 100ns for global reset to finish
        #100;
            ALUopcode = 0;//rega + regb
            rega = 1;
            regb = 1;

        #100;
            ALUopcode = 1;//rega - regb
            rega = 2;
            regb = 1;

        #100;
            ALUopcode = 1;//rega - regb
            rega = 1;
            regb = 2;

        #100;
            ALUopcode = 2;//rega & regb
            rega = 5;
            regb = 1;

        #100;
            ALUopcode = 3;//rega | regb
            rega = 4;
            regb = 1;

        #100;
            ALUopcode = 4;//rega < regb?不带符号比较
            rega = 4;
            regb = 5;

        #100;
            ALUopcode = 4;//rega < regb?不带符号比较
            rega = 5;
            regb = 4;

        #100;
            ALUopcode = 5;//rega < regb?带符号比较
            rega = 4;
            regb = 5;

        #100;
            ALUopcode = 5;//reg < regb?带符号比较
            rega = -1;
            regb = -2;

        #100;
            ALUopcode = 5;//reg < regb?带符号比较
            rega = -2;
            regb = -1;

        #100;
            ALUopcode = 5;//reg < regb?带符号比较
            rega = -1;
            regb = 0;

        #100;
            ALUopcode = 5;//reg < regb?带符号比较
            rega = 0;
            regb = -2;

        #100;
            ALUopcode = 5;//reg < regb?带符号比较
            rega = -1;
            regb = -1;
        
        #100;
            ALUopcode = 5;//reg < regb?带符号比较
            rega = 0;
            regb = 2;

        #100;
            ALUopcode = 5;//reg < regb?带符号比较
            rega = 1;
            regb = 0;

        #100;
            ALUopcode = 5;//reg < regb?带符号比较
            rega = 2;
            regb = 2;

        #100;
            ALUopcode = 5;//reg < regb?带符号比较
            rega = 0;
            regb = 0;

        #100;
            ALUopcode = 5;//reg < regb?带符号比较
            rega = 9;
            regb = 5;

        #100;
            $stop;
    end

endmodule

ALU/ALU32.vcd
$date
	Sun Nov 10 11:42:00 2019
$end
$version
	Icarus Verilog
$end
$timescale
	1s
$end
$scope module ALU32_sim $end
$var wire 1 ! zero $end
$var wire 1 " sign $end
$var wire 32 # result [31:0] $end
$var reg 3 $ ALUopcode [2:0] $end
$var reg 32 % rega [31:0] $end
$var reg 32 & regb [31:0] $end
$scope module uut $end
$var wire 3 ' ALUopcode [2:0] $end
$var wire 32 ( rega [31:0] $end
$var wire 32 ) regb [31:0] $end
$var wire 1 ! zero $end
$var wire 1 " sign $end
$var reg 32 * result [31:0] $end
$upscope $end
$upscope $end
$enddefinitions $end
#0
$dumpvars
b0 *
b0 )
b0 (
b0 '
b0 &
b0 %
b0 $
b0 #
0"
1!
$end
#100
0!
b10 #
b10 *
b1 &
b1 )
b1 %
b1 (
#200
b1 #
b1 *
b10 %
b10 (
b1 $
b1 '
#300
1"
b11111111111111111111111111111111 #
b11111111111111111111111111111111 *
b10 &
b10 )
b1 %
b1 (
#400
0"
b1 #
b1 *
b1 &
b1 )
b101 %
b101 (
b10 $
b10 '
#500
b101 #
b101 *
b100 %
b100 (
b11 $
b11 '
#600
b1 #
b1 *
b101 &
b101 )
b100 $
b100 '
#700
1!
b0 #
b0 *
b100 &
b100 )
b101 %
b101 (
#800
0!
b1 #
b1 *
b101 &
b101 )
b100 %
b100 (
b101 $
b101 '
#900
1!
b0 #
b0 *
b11111111111111111111111111111110 &
b11111111111111111111111111111110 )
b11111111111111111111111111111111 %
b11111111111111111111111111111111 (
#1000
0!
b1 #
b1 *
b11111111111111111111111111111111 &
b11111111111111111111111111111111 )
b11111111111111111111111111111110 %
b11111111111111111111111111111110 (
#1100
b0 &
b0 )
b11111111111111111111111111111111 %
b11111111111111111111111111111111 (
#1200
1!
b0 #
b0 *
b11111111111111111111111111111110 &
b11111111111111111111111111111110 )
b0 %
b0 (
#1300
b11111111111111111111111111111111 &
b11111111111111111111111111111111 )
b11111111111111111111111111111111 %
b11111111111111111111111111111111 (
#1400
0!
b1 #
b1 *
b10 &
b10 )
b0 %
b0 (
#1500
1!
b0 #
b0 *
b0 &
b0 )
b1 %
b1 (
#1600
b10 &
b10 )
b10 %
b10 (
#1700
b0 &
b0 )
b0 %
b0 (
#1800
b101 &
b101 )
b1001 %
b1001 (
